pyco/__init__.py
pyco/_private.py
pyco/color.py
pyco/constants.py
pyco/cursor.py
pyco/input.py
pyco/logging.py
pyco/prefix.py
pyco/progress.py
pyco/pyco.py
pyco/terminal.py
pyco/text.py
pyco/utils.py
pyco-1.0.0.dist-info/METADATA
pyco-1.0.0.dist-info/WHEEL
pyco-1.0.0.dist-info/license.txt
pyco-1.0.0.dist-info/top_level.txt
pyco-1.0.0.dist-info/RECORD
