Metadata-Version: 2.1
Name: pyco
Version: 1.0.0
Summary: Colorized console printing and input, ANSI escape codes, and logging functions.
Home-page: https://github.com/Duplexes/pyco
Author: Duplexes
Author-email: no@email.com
Maintainer: LemonPi314
License: MIT
Keywords: console,terminal,ansi,color,logging
Platform: UNKNOWN
Classifier: Programming Language :: Python :: 3
Classifier: Operating System :: OS Independent
Classifier: Environment :: Console
Classifier: Intended Audience :: Developers
Classifier: License :: OSI Approved :: MIT License
Requires-Python: >=3.6.8
License-File: license.txt
